Metadata-Version: 2.4
Name: ezcord
Version: 0.7.4
Summary: An easy-to-use extension for Discord.py and Pycord
Author: tibue99
License: MIT
Project-URL: GitHub, https://github.com/tibue99/ezcord
Project-URL: Documentation, https://ezcord.readthedocs.io
Keywords: discord,pycord,py-cord,discord.py
Classifier: Development Status :: 5 - Production/Stable
Classifier: License :: OSI Approved :: MIT License
Classifier: Intended Audience :: Developers
Classifier: Operating System :: OS Independent
Classifier: Topic :: Software Development :: Libraries
Classifier: Topic :: Software Development :: Libraries :: Python Modules
Classifier: Topic :: Utilities
Classifier: Programming Language :: Python :: 3.9
Classifier: Programming Language :: Python :: 3.10
Classifier: Programming Language :: Python :: 3.11
Classifier: Programming Language :: Python :: 3.12
Classifier: Programming Language :: Python :: 3.13
Requires-Python: >=3.9
License-File: LICENSE
Requires-Dist: aiocache
Requires-Dist: aiohttp
Requires-Dist: aiosqlite
Requires-Dist: colorama
Requires-Dist: python-dotenv
Requires-Dist: PyYAML
Requires-Dist: audioop-lts; python_version >= "3.13"
Provides-Extra: docs
Requires-Dist: py-cord; extra == "docs"
Requires-Dist: asyncpg; extra == "docs"
Requires-Dist: sphinx; extra == "docs"
Requires-Dist: furo; extra == "docs"
Requires-Dist: sphinx-autodoc-typehints; extra == "docs"
Requires-Dist: sphinx-copybutton; extra == "docs"
Dynamic: license-file
